LidlConnect/__init__.py
LidlConnect/auth.py
LidlConnect/client.py
LidlConnect/extractors.py
LidlConnect/helpers.py
LidlConnect/api/__init__.py
LidlConnect/api/credit.py
LidlConnect/api/invoices.py
LidlConnect/api/tariffs.py
LidlConnect/api/usage.py
LidlConnect/api/user.py
LidlConnect/api/utils.py
lidlconnect_py-0.1.2.dist-info/licenses/LICENSE
lidlconnect_py-0.1.2.dist-info/METADATA
lidlconnect_py-0.1.2.dist-info/WHEEL
lidlconnect_py-0.1.2.dist-info/top_level.txt
lidlconnect_py-0.1.2.dist-info/RECORD
