Metadata-Version: 2.4
Name: LidlConnect.py
Version: 0.1.2
Summary: Python API client for Lidl Connect
Author-email: Kizuren <info@kizuren.dev>
License: MIT License
Project-URL: Homepage, https://github.com/Kizuren/LidlConnect.py
License-File: LICENSE
Requires-Dist: bs4
Requires-Dist: requests
Dynamic: license-file
